[
  {
    "author": "bmt9",
    "link_thumb": "https://live.staticflickr.com/65535/51695257470_79808be6fd_o.gif",
    "link_bin": "https://github.com/lmbstudiocontact/mb5_3/raw/main/627.bin",
    "id_bin": "627",
    "list_language": [],
    "array_tags": [
      "date",
      "digital",
      "distance",
      "heartrate",
      "blackbackground",
      "calories",
      "battery",
      "steps"
    ],
    "list_album": [
      {
        "id_album": "2433880",
        "link_thumb": "https://live.staticflickr.com/65535/51695257470_79808be6fd_o.gif",
        "title": "None"
      }
    ]
  },
  {
    "author": "LMB Studio",
    "link_thumb": "https://live.staticflickr.com/65535/51698839588_af38559771_o.gif",
    "link_bin": "https://github.com/lmbstudiocontact/mb5_35/raw/main/Girl_L7_-988175517.bin",
    "id_bin": "Girl_L7_-988175517",
    "list_language": [],
    "array_tags": [
      "lmbstudio"
    ],
    "list_album": [
      {
        "id_album": "1702905294",
        "link_thumb": "https://live.staticflickr.com/65535/51698839588_af38559771_o.gif",
        "title": "Girl_L7"
      }
    ]
  },
  {
    "author": "iamstven",
    "link_thumb": "https://live.staticflickr.com/65535/51695085724_84f1297c63_o.gif",
    "link_bin": "https://github.com/lmbstudiocontact/mb5_3/raw/main/814.bin",
    "id_bin": "814",
    "list_language": [],
    "array_tags": [
      "weather",
      "battery",
      "steps"
    ],
    "list_album": [
      {
        "id_album": "2433880",
        "link_thumb": "https://live.staticflickr.com/65535/51695085724_84f1297c63_o.gif",
        "title": "None"
      }
    ]
  },
  {
    "author": "NeroNekro",
    "link_thumb": "https://live.staticflickr.com/65535/51695124239_43e178f243_o.gif",
    "link_bin": "https://github.com/lmbstudiocontact/mb5_23/raw/main/994.bin",
    "id_bin": "994",
    "list_language": [],
    "array_tags": [
      "date",
      "pulse"
    ],
    "list_album": [
      {
        "id_album": "63410260",
        "link_thumb": "https://live.staticflickr.com/65535/51695124239_43e178f243_o.gif",
        "title": "Anime"
      }
    ]
  },
  {
    "author": "LMB Studio",
    "link_thumb": "https://live.staticflickr.com/65535/51703987943_2f2c276d34_o.gif",
    "link_bin": "https://github.com/lmbstudiocontact/mb5_26/raw/main/Shiv_L5_1068394353.bin",
    "id_bin": "Shiv_L5_1068394353",
    "list_language": [
      {
        "author": "LMB Studio",
        "link_thumb": "https://live.staticflickr.com/65535/51703705736_61873d5029_o.gif",
        "link_bin": "https://github.com/lmbstudiocontact/mb5_26/raw/main/Shiv_L5_1068394353_English.bin",
        "name_language": "English",
        "id_bin_language": "Shiv_L5_1068394353_English"
      },
      {
        "author": "LMB Studio",
        "link_thumb": "https://live.staticflickr.com/65535/51703705856_cb75ac348d_o.gif",
        "link_bin": "https://github.com/lmbstudiocontact/mb5_26/raw/main/Shiv_L5_1068394353_Portuguese.bin",
        "name_language": "Portuguese",
        "id_bin_language": "Shiv_L5_1068394353_Portuguese"
      },
      {
        "author": "LMB Studio",
        "link_thumb": "https://live.staticflickr.com/65535/51703988348_d60aa54f2b_o.gif",
        "link_bin": "https://github.com/lmbstudiocontact/mb5_26/raw/main/Shiv_L5_1068394353_Russian.bin",
        "name_language": "Russian",
        "id_bin_language": "Shiv_L5_1068394353_Russian"
      },
      {
        "author": "LMB Studio",
        "link_thumb": "https://live.staticflickr.com/65535/51703706216_9209644e55_o.gif",
        "link_bin": "https://github.com/lmbstudiocontact/mb5_26/raw/main/Shiv_L5_1068394353_Spanish.bin",
        "name_language": "Spanish",
        "id_bin_language": "Shiv_L5_1068394353_Spanish"
      }
    ],
    "array_tags": [
      "lmbstudio"
    ],
    "list_album": [
      {
        "id_album": "-568595354",
        "link_thumb": "https://live.staticflickr.com/65535/51703987943_2f2c276d34_o.gif",
        "title": "Shiv_L5"
      }
    ]
  },
  {
    "author": "Carlinhos Dah",
    "link_thumb": "https://live.staticflickr.com/65535/51693371752_2c05cb0260_o.gif",
    "link_bin": "https://github.com/lmbstudiocontact/mb5_22/raw/main/2577.bin",
    "id_bin": "2577",
    "list_language": [],
    "array_tags": [],
    "list_album": [
      {
        "id_album": "2433880",
        "link_thumb": "https://live.staticflickr.com/65535/51693371752_2c05cb0260_o.gif",
        "title": "None"
      }
    ]
  },
  {
    "author": "LMB Studio",
    "link_thumb": "https://live.staticflickr.com/65535/51780949804_731e68e085_n.jpg",
    "link_bin": "https://github.com/lmbstudiocontact/mb5_28/raw/main/SpiderManCartoon_L3_664043828.bin",
    "id_bin": "SpiderManCartoon_L3_664043828",
    "list_language": [
      {
        "author": "LMB Studio",
        "link_thumb": "https://live.staticflickr.com/65535/51780949724_ded6380463_n.jpg",
        "link_bin": "https://github.com/lmbstudiocontact/mb5_28/raw/main/SpiderManCartoon_L3_664043828_English.bin",
        "name_language": "English",
        "id_bin_language": "SpiderManCartoon_L3_664043828_English"
      },
      {
        "author": "LMB Studio",
        "link_thumb": "https://live.staticflickr.com/65535/51781188010_f431d2daec_n.jpg",
        "link_bin": "https://github.com/lmbstudiocontact/mb5_28/raw/main/SpiderManCartoon_L3_664043828_Portuguese.bin",
        "name_language": "Portuguese",
        "id_bin_language": "SpiderManCartoon_L3_664043828_Portuguese"
      },
      {
        "author": "LMB Studio",
        "link_thumb": "https://live.staticflickr.com/65535/51780555488_77b80ae5bb_n.jpg",
        "link_bin": "https://github.com/lmbstudiocontact/mb5_28/raw/main/SpiderManCartoon_L3_664043828_Russian.bin",
        "name_language": "Russian",
        "id_bin_language": "SpiderManCartoon_L3_664043828_Russian"
      },
      {
        "author": "LMB Studio",
        "link_thumb": "https://live.staticflickr.com/65535/51779491532_2a93151c3d_n.jpg",
        "link_bin": "https://github.com/lmbstudiocontact/mb5_28/raw/main/SpiderManCartoon_L3_664043828_Spanish.bin",
        "name_language": "Spanish",
        "id_bin_language": "SpiderManCartoon_L3_664043828_Spanish"
      }
    ],
    "array_tags": [
      "lmbstudio"
    ],
    "list_album": [
      {
        "id_album": "1735002393",
        "link_thumb": "https://live.staticflickr.com/65535/51780949804_731e68e085_n.jpg",
        "title": "Spider Man Cartoon_L3"
      }
    ]
  },
  {
    "author": "LMB Studio",
    "link_thumb": "https://live.staticflickr.com/65535/51779527992_14af7beb65_n.jpg",
    "link_bin": "https://github.com/lmbstudiocontact/mb5_25/raw/main/SevendeadlysinsAnime_L4_840623172.bin",
    "id_bin": "SevendeadlysinsAnime_L4_840623172",
    "list_language": [
      {
        "author": "LMB Studio",
        "link_thumb": "https://live.staticflickr.com/65535/51780985954_3b2926b811_n.jpg",
        "link_bin": "https://github.com/lmbstudiocontact/mb5_25/raw/main/SevendeadlysinsAnime_L4_840623172_English.bin",
        "name_language": "English",
        "id_bin_language": "SevendeadlysinsAnime_L4_840623172_English"
      },
      {
        "author": "LMB Studio",
        "link_thumb": "https://live.staticflickr.com/65535/51781224615_83d6c88f96_n.jpg",
        "link_bin": "https://github.com/lmbstudiocontact/mb5_25/raw/main/SevendeadlysinsAnime_L4_840623172_Portuguese.bin",
        "name_language": "Portuguese",
        "id_bin_language": "SevendeadlysinsAnime_L4_840623172_Portuguese"
      },
      {
        "author": "LMB Studio",
        "link_thumb": "https://live.staticflickr.com/65535/51779527887_43064e8ab2_n.jpg",
        "link_bin": "https://github.com/lmbstudiocontact/mb5_25/raw/main/SevendeadlysinsAnime_L4_840623172_Russian.bin",
        "name_language": "Russian",
        "id_bin_language": "SevendeadlysinsAnime_L4_840623172_Russian"
      },
      {
        "author": "LMB Studio",
        "link_thumb": "https://live.staticflickr.com/65535/51780985879_69c43aed92_n.jpg",
        "link_bin": "https://github.com/lmbstudiocontact/mb5_25/raw/main/SevendeadlysinsAnime_L4_840623172_Spanish.bin",
        "name_language": "Spanish",
        "id_bin_language": "SevendeadlysinsAnime_L4_840623172_Spanish"
      }
    ],
    "array_tags": [
      "lmbstudio"
    ],
    "list_album": [
      {
        "id_album": "1802210940",
        "link_thumb": "https://live.staticflickr.com/65535/51779527992_14af7beb65_n.jpg",
        "title": "Seven deadly sins Anime_L4"
      }
    ]
  },
  {
    "author": "LMB Studio",
    "link_thumb": "https://live.staticflickr.com/65535/51780855509_fbd0a29be6_o.gif",
    "link_bin": "https://github.com/lmbstudiocontact/mb5_41/raw/main/KungFuPanda_L4_1124462739.bin",
    "id_bin": "KungFuPanda_L4_1124462739",
    "list_language": [
      {
        "author": "LMB Studio",
        "link_thumb": "https://live.staticflickr.com/65535/51780213411_fd77439dd6_o.gif",
        "link_bin": "https://github.com/lmbstudiocontact/mb5_41/raw/main/KungFuPanda_L4_1124462739_English.bin",
        "name_language": "English",
        "id_bin_language": "KungFuPanda_L4_1124462739_English"
      },
      {
        "author": "LMB Studio",
        "link_thumb": "https://live.staticflickr.com/65535/51780855374_5e5db987d4_o.gif",
        "link_bin": "https://github.com/lmbstudiocontact/mb5_41/raw/main/KungFuPanda_L4_1124462739_Portuguese.bin",
        "name_language": "Portuguese",
        "id_bin_language": "KungFuPanda_L4_1124462739_Portuguese"
      },
      {
        "author": "LMB Studio",
        "link_thumb": "https://live.staticflickr.com/65535/51781096375_734b8d16f6_o.gif",
        "link_bin": "https://github.com/lmbstudiocontact/mb5_41/raw/main/KungFuPanda_L4_1124462739_Russian.bin",
        "name_language": "Russian",
        "id_bin_language": "KungFuPanda_L4_1124462739_Russian"
      },
      {
        "author": "LMB Studio",
        "link_thumb": "https://live.staticflickr.com/65535/51780855194_af966b8be0_o.gif",
        "link_bin": "https://github.com/lmbstudiocontact/mb5_41/raw/main/KungFuPanda_L4_1124462739_Spanish.bin",
        "name_language": "Spanish",
        "id_bin_language": "KungFuPanda_L4_1124462739_Spanish"
      }
    ],
    "array_tags": [
      "lmbstudio"
    ],
    "list_album": [
      {
        "id_album": "1222783553",
        "link_thumb": "https://live.staticflickr.com/65535/51780855509_fbd0a29be6_o.gif",
        "title": "Kung Fu Panda_L4"
      }
    ]
  },
  {
    "author": "LMB Studio",
    "link_thumb": "https://live.staticflickr.com/65535/51704260155_e28f524b64_o.gif",
    "link_bin": "https://github.com/lmbstudiocontact/mb5_17/raw/main/Ragnarok_L5_-489242867.bin",
    "id_bin": "Ragnarok_L5_-489242867",
    "list_language": [
      {
        "author": "LMB Studio",
        "link_thumb": "https://live.staticflickr.com/65535/51702576207_2e36ea30a3_o.gif",
        "link_bin": "https://github.com/lmbstudiocontact/mb5_17/raw/main/Ragnarok_L5_-489242867_English.bin",
        "name_language": "English",
        "id_bin_language": "Ragnarok_L5_-489242867_English"
      },
      {
        "author": "LMB Studio",
        "link_thumb": "https://live.staticflickr.com/65535/51703372386_f77e661945_o.gif",
        "link_bin": "https://github.com/lmbstudiocontact/mb5_17/raw/main/Ragnarok_L5_-489242867_Portuguese.bin",
        "name_language": "Portuguese",
        "id_bin_language": "Ragnarok_L5_-489242867_Portuguese"
      },
      {
        "author": "LMB Studio",
        "link_thumb": "https://live.staticflickr.com/65535/51704047634_fd5a37602b_o.gif",
        "link_bin": "https://github.com/lmbstudiocontact/mb5_17/raw/main/Ragnarok_L5_-489242867_Russian.bin",
        "name_language": "Russian",
        "id_bin_language": "Ragnarok_L5_-489242867_Russian"
      },
      {
        "author": "LMB Studio",
        "link_thumb": "https://live.staticflickr.com/65535/51702576662_22368b6e0b_o.gif",
        "link_bin": "https://github.com/lmbstudiocontact/mb5_17/raw/main/Ragnarok_L5_-489242867_Spanish.bin",
        "name_language": "Spanish",
        "id_bin_language": "Ragnarok_L5_-489242867_Spanish"
      }
    ],
    "array_tags": [
      "lmbstudio"
    ],
    "list_album": [
      {
        "id_album": "1601322213",
        "link_thumb": "https://live.staticflickr.com/65535/51704260155_e28f524b64_o.gif",
        "title": "Ragnarok_L5"
      }
    ]
  },
  {
    "author": "LMB Studio",
    "link_thumb": "https://live.staticflickr.com/65535/51779417797_18fb5f1de0_o.gif",
    "link_bin": "https://github.com/lmbstudiocontact/mb5_44/raw/main/NarutoAnime_L3_-1510533041.bin",
    "id_bin": "NarutoAnime_L3_-1510533041",
    "list_language": [
      {
        "author": "LMB Studio",
        "link_thumb": "https://live.staticflickr.com/65535/51781116855_2bbeda7cec_o.gif",
        "link_bin": "https://github.com/lmbstudiocontact/mb5_44/raw/main/NarutoAnime_L3_-1510533041_English.bin",
        "name_language": "English",
        "id_bin_language": "NarutoAnime_L3_-1510533041_English"
      },
      {
        "author": "LMB Studio",
        "link_thumb": "https://live.staticflickr.com/65535/51780234116_6e318e037b_o.gif",
        "link_bin": "https://github.com/lmbstudiocontact/mb5_44/raw/main/NarutoAnime_L3_-1510533041_Portuguese.bin",
        "name_language": "Portuguese",
        "id_bin_language": "NarutoAnime_L3_-1510533041_Portuguese"
      },
      {
        "author": "LMB Studio",
        "link_thumb": "https://live.staticflickr.com/65535/51780483023_59fd7b55cc_o.gif",
        "link_bin": "https://github.com/lmbstudiocontact/mb5_44/raw/main/NarutoAnime_L3_-1510533041_Russian.bin",
        "name_language": "Russian",
        "id_bin_language": "NarutoAnime_L3_-1510533041_Russian"
      },
      {
        "author": "LMB Studio",
        "link_thumb": "https://live.staticflickr.com/65535/51780876219_202d7caa0e_o.gif",
        "link_bin": "https://github.com/lmbstudiocontact/mb5_44/raw/main/NarutoAnime_L3_-1510533041_Spanish.bin",
        "name_language": "Spanish",
        "id_bin_language": "NarutoAnime_L3_-1510533041_Spanish"
      }
    ],
    "array_tags": [
      "lmbstudio"
    ],
    "list_album": [
      {
        "id_album": "1894397985",
        "link_thumb": "https://live.staticflickr.com/65535/51779417797_18fb5f1de0_o.gif",
        "title": "Naruto Anime_L3"
      }
    ]
  },
  {
    "author": "jase724",
    "link_thumb": "https://live.staticflickr.com/65535/51694655883_6af664b7f5_o.gif",
    "link_bin": "https://github.com/lmbstudiocontact/mb5_3/raw/main/680.bin",
    "id_bin": "680",
    "list_language": [],
    "array_tags": [
      "digital",
      "date",
      "analog",
      "heartrate",
      "weather",
      "calories",
      "battery",
      "steps"
    ],
    "list_album": [
      {
        "id_album": "2433880",
        "link_thumb": "https://live.staticflickr.com/65535/51694655883_6af664b7f5_o.gif",
        "title": "None"
      }
    ]
  },
  {
    "author": "LMB Studio",
    "link_thumb": "https://live.staticflickr.com/65535/51780938249_d4760af908_o.gif",
    "link_bin": "https://github.com/lmbstudiocontact/mb5_45/raw/main/OnePieceAnime_L2_962948459.bin",
    "id_bin": "OnePieceAnime_L2_962948459",
    "list_language": [
      {
        "author": "LMB Studio",
        "link_thumb": "https://live.staticflickr.com/65535/51779479427_84ef14954c_o.gif",
        "link_bin": "https://github.com/lmbstudiocontact/mb5_45/raw/main/OnePieceAnime_L2_962948459_English.bin",
        "name_language": "English",
        "id_bin_language": "OnePieceAnime_L2_962948459_English"
      },
      {
        "author": "LMB Studio",
        "link_thumb": "https://live.staticflickr.com/65535/51779479337_88b482940c_o.gif",
        "link_bin": "https://github.com/lmbstudiocontact/mb5_45/raw/main/OnePieceAnime_L2_962948459_Portuguese.bin",
        "name_language": "Portuguese",
        "id_bin_language": "OnePieceAnime_L2_962948459_Portuguese"
      },
      {
        "author": "LMB Studio",
        "link_thumb": "https://live.staticflickr.com/65535/51781176455_fa08bce053_o.gif",
        "link_bin": "https://github.com/lmbstudiocontact/mb5_45/raw/main/OnePieceAnime_L2_962948459_Russian.bin",
        "name_language": "Russian",
        "id_bin_language": "OnePieceAnime_L2_962948459_Russian"
      },
      {
        "author": "LMB Studio",
        "link_thumb": "https://live.staticflickr.com/65535/51780543663_2d5c6e42ae_o.gif",
        "link_bin": "https://github.com/lmbstudiocontact/mb5_45/raw/main/OnePieceAnime_L2_962948459_Spanish.bin",
        "name_language": "Spanish",
        "id_bin_language": "OnePieceAnime_L2_962948459_Spanish"
      }
    ],
    "array_tags": [
      "lmbstudio"
    ],
    "list_album": [
      {
        "id_album": "1351456605",
        "link_thumb": "https://live.staticflickr.com/65535/51780938249_d4760af908_o.gif",
        "title": "One Piece Anime_L2"
      }
    ]
  },
  {
    "author": "LMB Studio",
    "link_thumb": "https://live.staticflickr.com/65535/51780509683_82bc7ecffc_o.gif",
    "link_bin": "https://github.com/lmbstudiocontact/mb5_43/raw/main/MyMelodyBunny_L7_-1506690093.bin",
    "id_bin": "MyMelodyBunny_L7_-1506690093",
    "list_language": [],
    "array_tags": [
      "lmbstudio"
    ],
    "list_album": [
      {
        "id_album": "1796214688",
        "link_thumb": "https://live.staticflickr.com/65535/51780509683_82bc7ecffc_o.gif",
        "title": "My Melody Bunny_L7"
      }
    ]
  },
  {
    "author": "LMB Studio",
    "link_thumb": "https://live.staticflickr.com/65535/51699415460_d4e4bf49e1_o.gif",
    "link_bin": "https://github.com/lmbstudiocontact/mb5_35/raw/main/Girl_L7_-239653464.bin",
    "id_bin": "Girl_L7_-239653464",
    "list_language": [],
    "array_tags": [
      "lmbstudio"
    ],
    "list_album": [
      {
        "id_album": "1702905294",
        "link_thumb": "https://live.staticflickr.com/65535/51699415460_d4e4bf49e1_o.gif",
        "title": "Girl_L7"
      }
    ]
  },
  {
    "author": "LMB Studio",
    "link_thumb": "https://live.staticflickr.com/65535/51698117770_3399597fbe_o.gif",
    "link_bin": "https://github.com/lmbstudiocontact/mb5_31/raw/main/Football_L1_380596880.bin",
    "id_bin": "Football_L1_380596880",
    "list_language": [],
    "array_tags": [
      "lmbstudio"
    ],
    "list_album": [
      {
        "id_album": "-371026089",
        "link_thumb": "https://live.staticflickr.com/65535/51698117770_3399597fbe_o.gif",
        "title": "Football_L1"
      }
    ]
  },
  {
    "author": "LMB Studio",
    "link_thumb": "https://live.staticflickr.com/65535/51779474067_40f5cd642f_o.gif",
    "link_bin": "https://github.com/lmbstudiocontact/mb5_46/raw/main/OnePieceAnime_L4_-945849352.bin",
    "id_bin": "OnePieceAnime_L4_-945849352",
    "list_language": [
      {
        "author": "LMB Studio",
        "link_thumb": "https://live.staticflickr.com/65535/51780932584_2f01499787_o.gif",
        "link_bin": "https://github.com/lmbstudiocontact/mb5_46/raw/main/OnePieceAnime_L4_-945849352_English.bin",
        "name_language": "English",
        "id_bin_language": "OnePieceAnime_L4_-945849352_English"
      },
      {
        "author": "LMB Studio",
        "link_thumb": "https://live.staticflickr.com/65535/51780289946_aae850566e_o.gif",
        "link_bin": "https://github.com/lmbstudiocontact/mb5_46/raw/main/OnePieceAnime_L4_-945849352_Portuguese.bin",
        "name_language": "Portuguese",
        "id_bin_language": "OnePieceAnime_L4_-945849352_Portuguese"
      },
      {
        "author": "LMB Studio",
        "link_thumb": "https://live.staticflickr.com/65535/51780932479_c27219bd8e_o.gif",
        "link_bin": "https://github.com/lmbstudiocontact/mb5_46/raw/main/OnePieceAnime_L4_-945849352_Russian.bin",
        "name_language": "Russian",
        "id_bin_language": "OnePieceAnime_L4_-945849352_Russian"
      },
      {
        "author": "LMB Studio",
        "link_thumb": "https://live.staticflickr.com/65535/51780538003_6430465e73_o.gif",
        "link_bin": "https://github.com/lmbstudiocontact/mb5_46/raw/main/OnePieceAnime_L4_-945849352_Spanish.bin",
        "name_language": "Spanish",
        "id_bin_language": "OnePieceAnime_L4_-945849352_Spanish"
      }
    ],
    "array_tags": [
      "lmbstudio"
    ],
    "list_album": [
      {
        "id_album": "1351456607",
        "link_thumb": "https://live.staticflickr.com/65535/51779474067_40f5cd642f_o.gif",
        "title": "One Piece Anime_L4"
      }
    ]
  },
  {
    "author": "rafikmattos",
    "link_thumb": "https://live.staticflickr.com/65535/51694477683_a2a3416866_o.gif",
    "link_bin": "https://github.com/lmbstudiocontact/mb5_22/raw/main/2902.bin",
    "id_bin": "2902",
    "list_language": [],
    "array_tags": [
      "digital",
      "date",
      "miband5",
      "heartrate",
      "weather",
      "battery",
      "steps"
    ],
    "list_album": [
      {
        "id_album": "2433880",
        "link_thumb": "https://live.staticflickr.com/65535/51694477683_a2a3416866_o.gif",
        "title": "None"
      }
    ]
  },
  {
    "author": "LMB Studio",
    "link_thumb": "https://live.staticflickr.com/65535/51694814082_90644327df_o.gif",
    "link_bin": "https://github.com/lmbstudiocontact/mb5_28/raw/main/Couple_L1_380595764.bin",
    "id_bin": "Couple_L1_380595764",
    "list_language": [],
    "array_tags": [
      "lmbstudio"
    ],
    "list_album": [
      {
        "id_album": "-888889820",
        "link_thumb": "https://live.staticflickr.com/65535/51694814082_90644327df_o.gif",
        "title": "Couple_L1"
      }
    ]
  },
  {
    "author": "LMB Studio",
    "link_thumb": "https://live.staticflickr.com/65535/51703132119_810442c76e_o.gif",
    "link_bin": "https://github.com/lmbstudiocontact/mb5_20/raw/main/Pig_L7_-305534458.bin",
    "id_bin": "Pig_L7_-305534458",
    "list_language": [],
    "array_tags": [
      "lmbstudio"
    ],
    "list_album": [
      {
        "id_album": "-1904503332",
        "link_thumb": "https://live.staticflickr.com/65535/51703132119_810442c76e_o.gif",
        "title": "Pig_L7"
      }
    ]
  },
  {
    "author": "LMB Studio",
    "link_thumb": "https://live.staticflickr.com/65535/51703145150_405264a566_o.gif",
    "link_bin": "https://github.com/lmbstudiocontact/mb5_19/raw/main/Other_L7_1638458439.bin",
    "id_bin": "Other_L7_1638458439",
    "list_language": [],
    "array_tags": [
      "lmbstudio"
    ],
    "list_album": [
      {
        "id_album": "-1106495206",
        "link_thumb": "https://live.staticflickr.com/65535/51703145150_405264a566_o.gif",
        "title": "Other_L7"
      }
    ]
  },
  {
    "author": "LMB Studio",
    "link_thumb": "https://live.staticflickr.com/65535/51697749652_2be1e33d1e_o.gif",
    "link_bin": "https://github.com/lmbstudiocontact/mb5_35/raw/main/Girl_L7_-525202864.bin",
    "id_bin": "Girl_L7_-525202864",
    "list_language": [],
    "array_tags": [
      "lmbstudio"
    ],
    "list_album": [
      {
        "id_album": "1702905294",
        "link_thumb": "https://live.staticflickr.com/65535/51697749652_2be1e33d1e_o.gif",
        "title": "Girl_L7"
      }
    ]
  },
  {
    "author": "LMB Studio",
    "link_thumb": "https://live.staticflickr.com/65535/51695334109_ea346d6a4d_o.gif",
    "link_bin": "https://github.com/lmbstudiocontact/mb5_7/raw/main/Animal_L7_1160821595.bin",
    "id_bin": "Animal_L7_1160821595",
    "list_language": [],
    "array_tags": [
      "lmbstudio"
    ],
    "list_album": [
      {
        "id_album": "-1172738450",
        "link_thumb": "https://live.staticflickr.com/65535/51695334109_ea346d6a4d_o.gif",
        "title": "Animal_L7"
      }
    ]
  },
  {
    "author": "LMB Studio",
    "link_thumb": "https://live.staticflickr.com/65535/51703631896_28b3c05111_o.gif",
    "link_bin": "https://github.com/lmbstudiocontact/mb5_25/raw/main/Shiv_L2_-809361748.bin",
    "id_bin": "Shiv_L2_-809361748",
    "list_language": [
      {
        "author": "LMB Studio",
        "link_thumb": "https://live.staticflickr.com/65535/51704520845_b7be7b42c1_o.gif",
        "link_bin": "https://github.com/lmbstudiocontact/mb5_25/raw/main/Shiv_L2_-809361748_English.bin",
        "name_language": "English",
        "id_bin_language": "Shiv_L2_-809361748_English"
      },
      {
        "author": "LMB Studio",
        "link_thumb": "https://live.staticflickr.com/65535/51703632411_3e41dc3d4d_o.gif",
        "link_bin": "https://github.com/lmbstudiocontact/mb5_25/raw/main/Shiv_L2_-809361748_Portuguese.bin",
        "name_language": "Portuguese",
        "id_bin_language": "Shiv_L2_-809361748_Portuguese"
      },
      {
        "author": "LMB Studio",
        "link_thumb": "https://live.staticflickr.com/65535/51703914998_f04976ed47_o.gif",
        "link_bin": "https://github.com/lmbstudiocontact/mb5_25/raw/main/Shiv_L2_-809361748_Russian.bin",
        "name_language": "Russian",
        "id_bin_language": "Shiv_L2_-809361748_Russian"
      },
      {
        "author": "LMB Studio",
        "link_thumb": "https://live.staticflickr.com/65535/51703632811_79c6b79f3e_o.gif",
        "link_bin": "https://github.com/lmbstudiocontact/mb5_25/raw/main/Shiv_L2_-809361748_Spanish.bin",
        "name_language": "Spanish",
        "id_bin_language": "Shiv_L2_-809361748_Spanish"
      }
    ],
    "array_tags": [
      "lmbstudio"
    ],
    "list_album": [
      {
        "id_album": "-568595357",
        "link_thumb": "https://live.staticflickr.com/65535/51703631896_28b3c05111_o.gif",
        "title": "Shiv_L2"
      }
    ]
  },
  {
    "author": "LMB Studio",
    "link_thumb": "https://live.staticflickr.com/65535/51779390207_4725210c5c_o.gif",
    "link_bin": "https://github.com/lmbstudiocontact/mb5_40/raw/main/KittyMyMelody_L3_1188263347.bin",
    "id_bin": "KittyMyMelody_L3_1188263347",
    "list_language": [
      {
        "author": "LMB Studio",
        "link_thumb": "https://live.staticflickr.com/65535/51780206856_142fd722e2_o.gif",
        "link_bin": "https://github.com/lmbstudiocontact/mb5_40/raw/main/KittyMyMelody_L3_1188263347_English.bin",
        "name_language": "English",
        "id_bin_language": "KittyMyMelody_L3_1188263347_English"
      },
      {
        "author": "LMB Studio",
        "link_thumb": "https://live.staticflickr.com/65535/51780455688_6b2cff1e17_o.gif",
        "link_bin": "https://github.com/lmbstudiocontact/mb5_40/raw/main/KittyMyMelody_L3_1188263347_Portuguese.bin",
        "name_language": "Portuguese",
        "id_bin_language": "KittyMyMelody_L3_1188263347_Portuguese"
      },
      {
        "author": "LMB Studio",
        "link_thumb": "https://live.staticflickr.com/65535/51780848594_f0e166fef1_o.gif",
        "link_bin": "https://github.com/lmbstudiocontact/mb5_40/raw/main/KittyMyMelody_L3_1188263347_Russian.bin",
        "name_language": "Russian",
        "id_bin_language": "KittyMyMelody_L3_1188263347_Russian"
      },
      {
        "author": "LMB Studio",
        "link_thumb": "https://live.staticflickr.com/65535/51780455538_c429f85516_o.gif",
        "link_bin": "https://github.com/lmbstudiocontact/mb5_40/raw/main/KittyMyMelody_L3_1188263347_Spanish.bin",
        "name_language": "Spanish",
        "id_bin_language": "KittyMyMelody_L3_1188263347_Spanish"
      }
    ],
    "array_tags": [
      "lmbstudio"
    ],
    "list_album": [
      {
        "id_album": "-378480543",
        "link_thumb": "https://live.staticflickr.com/65535/51779390207_4725210c5c_o.gif",
        "title": "Kitty \u0026 My Melody_L3"
      }
    ]
  },
  {
    "author": "LMB Studio",
    "link_thumb": "https://live.staticflickr.com/65535/51702538572_0b6da4c46d_o.gif",
    "link_bin": "https://github.com/lmbstudiocontact/mb5_17/raw/main/Ragnarok_L1_380598616.bin",
    "id_bin": "Ragnarok_L1_380598616",
    "list_language": [],
    "array_tags": [
      "lmbstudio"
    ],
    "list_album": [
      {
        "id_album": "1601322209",
        "link_thumb": "https://live.staticflickr.com/65535/51702538572_0b6da4c46d_o.gif",
        "title": "Ragnarok_L1"
      }
    ]
  },
  {
    "author": "LMB Studio",
    "link_thumb": "https://live.staticflickr.com/65535/51779504992_3876357916_n.jpg",
    "link_bin": "https://github.com/lmbstudiocontact/mb5_18/raw/main/SevendeadlysinsAnime_L2_-1097181974.bin",
    "id_bin": "SevendeadlysinsAnime_L2_-1097181974",
    "list_language": [
      {
        "author": "LMB Studio",
        "link_thumb": "https://live.staticflickr.com/65535/51780569028_b6955b8f7c_n.jpg",
        "link_bin": "https://github.com/lmbstudiocontact/mb5_18/raw/main/SevendeadlysinsAnime_L2_-1097181974_English.bin",
        "name_language": "English",
        "id_bin_language": "SevendeadlysinsAnime_L2_-1097181974_English"
      },
      {
        "author": "LMB Studio",
        "link_thumb": "https://live.staticflickr.com/65535/51779504632_36e922739a_n.jpg",
        "link_bin": "https://github.com/lmbstudiocontact/mb5_18/raw/main/SevendeadlysinsAnime_L2_-1097181974_Portuguese.bin",
        "name_language": "Portuguese",
        "id_bin_language": "SevendeadlysinsAnime_L2_-1097181974_Portuguese"
      },
      {
        "author": "LMB Studio",
        "link_thumb": "https://live.staticflickr.com/65535/51780568893_fb8ce88c68_n.jpg",
        "link_bin": "https://github.com/lmbstudiocontact/mb5_18/raw/main/SevendeadlysinsAnime_L2_-1097181974_Russian.bin",
        "name_language": "Russian",
        "id_bin_language": "SevendeadlysinsAnime_L2_-1097181974_Russian"
      },
      {
        "author": "LMB Studio",
        "link_thumb": "https://live.staticflickr.com/65535/51780568853_5d13f56a8f_n.jpg",
        "link_bin": "https://github.com/lmbstudiocontact/mb5_18/raw/main/SevendeadlysinsAnime_L2_-1097181974_Spanish.bin",
        "name_language": "Spanish",
        "id_bin_language": "SevendeadlysinsAnime_L2_-1097181974_Spanish"
      }
    ],
    "array_tags": [
      "lmbstudio"
    ],
    "list_album": [
      {
        "id_album": "1802210938",
        "link_thumb": "https://live.staticflickr.com/65535/51779504992_3876357916_n.jpg",
        "title": "Seven deadly sins Anime_L2"
      }
    ]
  },
  {
    "author": "LMB Studio",
    "link_thumb": "https://live.staticflickr.com/65535/51780976329_52dc9705bc_n.jpg",
    "link_bin": "https://github.com/lmbstudiocontact/mb5_18/raw/main/Rio2_L5_-1677048440.bin",
    "id_bin": "Rio2_L5_-1677048440",
    "list_language": [
      {
        "author": "LMB Studio",
        "link_thumb": "https://live.staticflickr.com/65535/51781215020_cff7630d5f_n.jpg",
        "link_bin": "https://github.com/lmbstudiocontact/mb5_18/raw/main/Rio2_L5_-1677048440_English.bin",
        "name_language": "English",
        "id_bin_language": "Rio2_L5_-1677048440_English"
      },
      {
        "author": "LMB Studio",
        "link_thumb": "https://live.staticflickr.com/65535/51781214960_15c1cf890b_n.jpg",
        "link_bin": "https://github.com/lmbstudiocontact/mb5_18/raw/main/Rio2_L5_-1677048440_Portuguese.bin",
        "name_language": "Portuguese",
        "id_bin_language": "Rio2_L5_-1677048440_Portuguese"
      },
      {
        "author": "LMB Studio",
        "link_thumb": "https://live.staticflickr.com/65535/51781214890_78d4115019_n.jpg",
        "link_bin": "https://github.com/lmbstudiocontact/mb5_18/raw/main/Rio2_L5_-1677048440_Russian.bin",
        "name_language": "Russian",
        "id_bin_language": "Rio2_L5_-1677048440_Russian"
      },
      {
        "author": "LMB Studio",
        "link_thumb": "https://live.staticflickr.com/65535/51780333801_26b213e959_n.jpg",
        "link_bin": "https://github.com/lmbstudiocontact/mb5_18/raw/main/Rio2_L5_-1677048440_Spanish.bin",
        "name_language": "Spanish",
        "id_bin_language": "Rio2_L5_-1677048440_Spanish"
      }
    ],
    "array_tags": [
      "lmbstudio"
    ],
    "list_album": [
      {
        "id_album": "-1210862914",
        "link_thumb": "https://live.staticflickr.com/65535/51780976329_52dc9705bc_n.jpg",
        "title": "Rio 2_L5"
      }
    ]
  },
  {
    "author": "LMB Studio",
    "link_thumb": "https://live.staticflickr.com/65535/51704294699_423bab7125_o.gif",
    "link_bin": "https://github.com/lmbstudiocontact/mb5_25/raw/main/Shiv_L1_380596818.bin",
    "id_bin": "Shiv_L1_380596818",
    "list_language": [],
    "array_tags": [
      "lmbstudio"
    ],
    "list_album": [
      {
        "id_album": "-568595358",
        "link_thumb": "https://live.staticflickr.com/65535/51704294699_423bab7125_o.gif",
        "title": "Shiv_L1"
      }
    ]
  },
  {
    "author": "LMB Studio",
    "link_thumb": "https://live.staticflickr.com/65535/51780464113_9fcf263293_o.gif",
    "link_bin": "https://github.com/lmbstudiocontact/mb5_38/raw/main/MickeyCartoon_L2_861607461.bin",
    "id_bin": "MickeyCartoon_L2_861607461",
    "list_language": [
      {
        "author": "LMB Studio",
        "link_thumb": "https://live.staticflickr.com/65535/51781098355_814cda96a4_o.gif",
        "link_bin": "https://github.com/lmbstudiocontact/mb5_38/raw/main/MickeyCartoon_L2_861607461_English.bin",
        "name_language": "English",
        "id_bin_language": "MickeyCartoon_L2_861607461_English"
      },
      {
        "author": "LMB Studio",
        "link_thumb": "https://live.staticflickr.com/65535/51779398712_2fb08e66e9_o.gif",
        "link_bin": "https://github.com/lmbstudiocontact/mb5_38/raw/main/MickeyCartoon_L2_861607461_Portuguese.bin",
        "name_language": "Portuguese",
        "id_bin_language": "MickeyCartoon_L2_861607461_Portuguese"
      },
      {
        "author": "LMB Studio",
        "link_thumb": "https://live.staticflickr.com/65535/51780463928_14d62c98ca_o.gif",
        "link_bin": "https://github.com/lmbstudiocontact/mb5_38/raw/main/MickeyCartoon_L2_861607461_Russian.bin",
        "name_language": "Russian",
        "id_bin_language": "MickeyCartoon_L2_861607461_Russian"
      },
      {
        "author": "LMB Studio",
        "link_thumb": "https://live.staticflickr.com/65535/51779398547_90e72421ab_o.gif",
        "link_bin": "https://github.com/lmbstudiocontact/mb5_38/raw/main/MickeyCartoon_L2_861607461_Spanish.bin",
        "name_language": "Spanish",
        "id_bin_language": "MickeyCartoon_L2_861607461_Spanish"
      }
    ],
    "array_tags": [
      "lmbstudio"
    ],
    "list_album": [
      {
        "id_album": "1680949823",
        "link_thumb": "https://live.staticflickr.com/65535/51780464113_9fcf263293_o.gif",
        "title": "Mickey Cartoon_L2"
      }
    ]
  },
  {
    "author": "jsalvadorcm",
    "link_thumb": "https://live.staticflickr.com/65535/51694182071_2d7208dc09_o.gif",
    "link_bin": "https://github.com/lmbstudiocontact/mb5_22/raw/main/2740.bin",
    "id_bin": "2740",
    "list_language": [],
    "array_tags": [
      "digital",
      "disney",
      "retro",
      "simple"
    ],
    "list_album": [
      {
        "id_album": "-2075887794",
        "link_thumb": "https://live.staticflickr.com/65535/51694182071_2d7208dc09_o.gif",
        "title": "Cartoon"
      }
    ]
  },
  {
    "author": "LMB Studio",
    "link_thumb": "https://live.staticflickr.com/65535/51698628833_573d528f46_o.gif",
    "link_bin": "https://github.com/lmbstudiocontact/mb5_34/raw/main/Girl_L6_-944582431.bin",
    "id_bin": "Girl_L6_-944582431",
    "list_language": [
      {
        "author": "LMB Studio",
        "link_thumb": "https://live.staticflickr.com/65535/51698629363_ae10f9ef61_o.gif",
        "link_bin": "https://github.com/lmbstudiocontact/mb5_34/raw/main/Girl_L6_-944582431_English.bin",
        "name_language": "English",
        "id_bin_language": "Girl_L6_-944582431_English"
      },
      {
        "author": "LMB Studio",
        "link_thumb": "https://live.staticflickr.com/65535/51697560022_70501a72e1_o.gif",
        "link_bin": "https://github.com/lmbstudiocontact/mb5_34/raw/main/Girl_L6_-944582431_Portuguese.bin",
        "name_language": "Portuguese",
        "id_bin_language": "Girl_L6_-944582431_Portuguese"
      },
      {
        "author": "LMB Studio",
        "link_thumb": "https://live.staticflickr.com/65535/51699027274_4a897ec4be_o.gif",
        "link_bin": "https://github.com/lmbstudiocontact/mb5_34/raw/main/Girl_L6_-944582431_Russian.bin",
        "name_language": "Russian",
        "id_bin_language": "Girl_L6_-944582431_Russian"
      },
      {
        "author": "LMB Studio",
        "link_thumb": "https://live.staticflickr.com/65535/51698352576_2814bd8052_o.gif",
        "link_bin": "https://github.com/lmbstudiocontact/mb5_34/raw/main/Girl_L6_-944582431_Spanish.bin",
        "name_language": "Spanish",
        "id_bin_language": "Girl_L6_-944582431_Spanish"
      }
    ],
    "array_tags": [
      "lmbstudio"
    ],
    "list_album": [
      {
        "id_album": "1702905293",
        "link_thumb": "https://live.staticflickr.com/65535/51698628833_573d528f46_o.gif",
        "title": "Girl_L6"
      }
    ]
  },
  {
    "author": "LMB Studio",
    "link_thumb": "https://live.staticflickr.com/65535/51781124930_8e7d5b9ae5_o.gif",
    "link_bin": "https://github.com/lmbstudiocontact/mb5_39/raw/main/KittyMyMelody_L2_521381685.bin",
    "id_bin": "KittyMyMelody_L2_521381685",
    "list_language": [
      {
        "author": "LMB Studio",
        "link_thumb": "https://live.staticflickr.com/65535/51780490928_2085f01736_o.gif",
        "link_bin": "https://github.com/lmbstudiocontact/mb5_39/raw/main/KittyMyMelody_L2_521381685_English.bin",
        "name_language": "English",
        "id_bin_language": "KittyMyMelody_L2_521381685_English"
      },
      {
        "author": "LMB Studio",
        "link_thumb": "https://live.staticflickr.com/65535/51780884909_62a23964b7_o.gif",
        "link_bin": "https://github.com/lmbstudiocontact/mb5_39/raw/main/KittyMyMelody_L2_521381685_Portuguese.bin",
        "name_language": "Portuguese",
        "id_bin_language": "KittyMyMelody_L2_521381685_Portuguese"
      },
      {
        "author": "LMB Studio",
        "link_thumb": "https://live.staticflickr.com/65535/51780242201_b7a3c1d370_o.gif",
        "link_bin": "https://github.com/lmbstudiocontact/mb5_39/raw/main/KittyMyMelody_L2_521381685_Russian.bin",
        "name_language": "Russian",
        "id_bin_language": "KittyMyMelody_L2_521381685_Russian"
      },
      {
        "author": "LMB Studio",
        "link_thumb": "https://live.staticflickr.com/65535/51780242141_345d1ffd90_o.gif",
        "link_bin": "https://github.com/lmbstudiocontact/mb5_39/raw/main/KittyMyMelody_L2_521381685_Spanish.bin",
        "name_language": "Spanish",
        "id_bin_language": "KittyMyMelody_L2_521381685_Spanish"
      }
    ],
    "array_tags": [
      "lmbstudio"
    ],
    "list_album": [
      {
        "id_album": "-378480544",
        "link_thumb": "https://live.staticflickr.com/65535/51781124930_8e7d5b9ae5_o.gif",
        "title": "Kitty \u0026 My Melody_L2"
      }
    ]
  },
  {
    "author": "LMB Studio",
    "link_thumb": "https://live.staticflickr.com/65535/51781218445_a06258273c_n.jpg",
    "link_bin": "https://github.com/lmbstudiocontact/mb5_18/raw/main/Rio2_L5_-139447600.bin",
    "id_bin": "Rio2_L5_-139447600",
    "list_language": [
      {
        "author": "LMB Studio",
        "link_thumb": "https://live.staticflickr.com/65535/51780337311_0e7fef2db1_n.jpg",
        "link_bin": "https://github.com/lmbstudiocontact/mb5_18/raw/main/Rio2_L5_-139447600_English.bin",
        "name_language": "English",
        "id_bin_language": "Rio2_L5_-139447600_English"
      },
      {
        "author": "LMB Studio",
        "link_thumb": "https://live.staticflickr.com/65535/51780979729_af4e1a6e53_n.jpg",
        "link_bin": "https://github.com/lmbstudiocontact/mb5_18/raw/main/Rio2_L5_-139447600_Portuguese.bin",
        "name_language": "Portuguese",
        "id_bin_language": "Rio2_L5_-139447600_Portuguese"
      },
      {
        "author": "LMB Studio",
        "link_thumb": "https://live.staticflickr.com/65535/51781218250_2603a5e9bc_n.jpg",
        "link_bin": "https://github.com/lmbstudiocontact/mb5_18/raw/main/Rio2_L5_-139447600_Russian.bin",
        "name_language": "Russian",
        "id_bin_language": "Rio2_L5_-139447600_Russian"
      },
      {
        "author": "LMB Studio",
        "link_thumb": "https://live.staticflickr.com/65535/51780337191_6c214bc1fe_n.jpg",
        "link_bin": "https://github.com/lmbstudiocontact/mb5_18/raw/main/Rio2_L5_-139447600_Spanish.bin",
        "name_language": "Spanish",
        "id_bin_language": "Rio2_L5_-139447600_Spanish"
      }
    ],
    "array_tags": [
      "lmbstudio"
    ],
    "list_album": [
      {
        "id_album": "-1210862914",
        "link_thumb": "https://live.staticflickr.com/65535/51781218445_a06258273c_n.jpg",
        "title": "Rio 2_L5"
      }
    ]
  },
  {
    "author": "LMB Studio",
    "link_thumb": "https://live.staticflickr.com/65535/51780415948_a664f71688_o.gif",
    "link_bin": "https://github.com/lmbstudiocontact/mb5_14/raw/main/CuteArt_L4_-1605059636.bin",
    "id_bin": "CuteArt_L4_-1605059636",
    "list_language": [
      {
        "author": "LMB Studio",
        "link_thumb": "https://live.staticflickr.com/65535/51779350472_9ca74437d5_o.gif",
        "link_bin": "https://github.com/lmbstudiocontact/mb5_14/raw/main/CuteArt_L4_-1605059636_English.bin",
        "name_language": "English",
        "id_bin_language": "CuteArt_L4_-1605059636_English"
      },
      {
        "author": "LMB Studio",
        "link_thumb": "https://live.staticflickr.com/65535/51780167121_2a969f97e8_o.gif",
        "link_bin": "https://github.com/lmbstudiocontact/mb5_14/raw/main/CuteArt_L4_-1605059636_Portuguese.bin",
        "name_language": "Portuguese",
        "id_bin_language": "CuteArt_L4_-1605059636_Portuguese"
      },
      {
        "author": "LMB Studio",
        "link_thumb": "https://live.staticflickr.com/65535/51781050160_842e1f68b5_o.gif",
        "link_bin": "https://github.com/lmbstudiocontact/mb5_14/raw/main/CuteArt_L4_-1605059636_Russian.bin",
        "name_language": "Russian",
        "id_bin_language": "CuteArt_L4_-1605059636_Russian"
      },
      {
        "author": "LMB Studio",
        "link_thumb": "https://live.staticflickr.com/65535/51781050120_da1fcbf33b_o.gif",
        "link_bin": "https://github.com/lmbstudiocontact/mb5_14/raw/main/CuteArt_L4_-1605059636_Spanish.bin",
        "name_language": "Spanish",
        "id_bin_language": "CuteArt_L4_-1605059636_Spanish"
      }
    ],
    "array_tags": [
      "lmbstudio"
    ],
    "list_album": [
      {
        "id_album": "-629963487",
        "link_thumb": "https://live.staticflickr.com/65535/51780415948_a664f71688_o.gif",
        "title": "Cute Art_L4"
      }
    ]
  },
  {
    "author": "LMB Studio",
    "link_thumb": "https://live.staticflickr.com/65535/51780528603_e8a391d48c_o.gif",
    "link_bin": "https://github.com/lmbstudiocontact/mb5_9/raw/main/OnePieceAnime_L1_2028308101.bin",
    "id_bin": "OnePieceAnime_L1_2028308101",
    "list_language": [],
    "array_tags": [
      "lmbstudio"
    ],
    "list_album": [
      {
        "id_album": "1351456604",
        "link_thumb": "https://live.staticflickr.com/65535/51780528603_e8a391d48c_o.gif",
        "title": "One Piece Anime_L1"
      }
    ]
  },
  {
    "author": "LMB Studio",
    "link_thumb": "https://live.staticflickr.com/65535/51694752751_886dabf617_o.gif",
    "link_bin": "https://github.com/lmbstudiocontact/mb5_9/raw/main/Bear_L6_-525203697.bin",
    "id_bin": "Bear_L6_-525203697",
    "list_language": [
      {
        "author": "LMB Studio",
        "link_thumb": "https://live.staticflickr.com/65535/51695026683_e28943a52a_o.gif",
        "link_bin": "https://github.com/lmbstudiocontact/mb5_9/raw/main/Bear_L6_-525203697_English.bin",
        "name_language": "English",
        "id_bin_language": "Bear_L6_-525203697_English"
      },
      {
        "author": "LMB Studio",
        "link_thumb": "https://live.staticflickr.com/65535/51695640120_31e427714b_o.gif",
        "link_bin": "https://github.com/lmbstudiocontact/mb5_9/raw/main/Bear_L6_-525203697_Portuguese.bin",
        "name_language": "Portuguese",
        "id_bin_language": "Bear_L6_-525203697_Portuguese"
      },
      {
        "author": "LMB Studio",
        "link_thumb": "https://live.staticflickr.com/65535/51695027033_b04479a735_o.gif",
        "link_bin": "https://github.com/lmbstudiocontact/mb5_9/raw/main/Bear_L6_-525203697_Russian.bin",
        "name_language": "Russian",
        "id_bin_language": "Bear_L6_-525203697_Russian"
      },
      {
        "author": "LMB Studio",
        "link_thumb": "https://live.staticflickr.com/65535/51694753651_23a8143596_o.gif",
        "link_bin": "https://github.com/lmbstudiocontact/mb5_9/raw/main/Bear_L6_-525203697_Spanish.bin",
        "name_language": "Spanish",
        "id_bin_language": "Bear_L6_-525203697_Spanish"
      }
    ],
    "array_tags": [
      "lmbstudio"
    ],
    "list_album": [
      {
        "id_album": "1430316469",
        "link_thumb": "https://live.staticflickr.com/65535/51694752751_886dabf617_o.gif",
        "title": "Bear_L6"
      }
    ]
  },
  {
    "author": "LMB Studio",
    "link_thumb": "https://live.staticflickr.com/65535/51693856737_0a809a8cfe_o.gif",
    "link_bin": "https://github.com/lmbstudiocontact/mb5_7/raw/main/Animal_L7_-239651634.bin",
    "id_bin": "Animal_L7_-239651634",
    "list_language": [],
    "array_tags": [
      "lmbstudio"
    ],
    "list_album": [
      {
        "id_album": "-1172738450",
        "link_thumb": "https://live.staticflickr.com/65535/51693856737_0a809a8cfe_o.gif",
        "title": "Animal_L7"
      }
    ]
  },
  {
    "author": "rafikmattos",
    "link_thumb": "https://live.staticflickr.com/65535/51694203381_a996fd0f96_o.gif",
    "link_bin": "https://github.com/lmbstudiocontact/mb5_22/raw/main/2896.bin",
    "id_bin": "2896",
    "list_language": [],
    "array_tags": [
      "digital",
      "date",
      "miband5",
      "heartrate",
      "weather",
      "battery",
      "steps"
    ],
    "list_album": [
      {
        "id_album": "2433880",
        "link_thumb": "https://live.staticflickr.com/65535/51694203381_a996fd0f96_o.gif",
        "title": "None"
      }
    ]
  },
  {
    "author": "LMB Studio",
    "link_thumb": "https://live.staticflickr.com/65535/51694370162_2d818ff920_o.gif",
    "link_bin": "https://github.com/lmbstudiocontact/mb5_3/raw/main/Boy_L7_-305626779.bin",
    "id_bin": "Boy_L7_-305626779",
    "list_language": [],
    "array_tags": [
      "lmbstudio"
    ],
    "list_album": [
      {
        "id_album": "1995733214",
        "link_thumb": "https://live.staticflickr.com/65535/51694370162_2d818ff920_o.gif",
        "title": "Boy_L7"
      }
    ]
  },
  {
    "author": "LMB Studio",
    "link_thumb": "https://live.staticflickr.com/65535/51697916339_2a5d1ecc0e_o.gif",
    "link_bin": "https://github.com/lmbstudiocontact/mb5_31/raw/main/Football_L1_380598678.bin",
    "id_bin": "Football_L1_380598678",
    "list_language": [],
    "array_tags": [
      "lmbstudio"
    ],
    "list_album": [
      {
        "id_album": "-371026089",
        "link_thumb": "https://live.staticflickr.com/65535/51697916339_2a5d1ecc0e_o.gif",
        "title": "Football_L1"
      }
    ]
  },
  {
    "author": "LMB Studio",
    "link_thumb": "https://live.staticflickr.com/65535/51780526113_90f8534691_n.jpg",
    "link_bin": "https://github.com/lmbstudiocontact/mb5_18/raw/main/Rio2_L2_72027508.bin",
    "id_bin": "Rio2_L2_72027508",
    "list_language": [
      {
        "author": "LMB Studio",
        "link_thumb": "https://live.staticflickr.com/65535/51781159160_a9cd0fee71_n.jpg",
        "link_bin": "https://github.com/lmbstudiocontact/mb5_18/raw/main/Rio2_L2_72027508_English.bin",
        "name_language": "English",
        "id_bin_language": "Rio2_L2_72027508_English"
      },
      {
        "author": "LMB Studio",
        "link_thumb": "https://live.staticflickr.com/65535/51780277651_e550d592b5_n.jpg",
        "link_bin": "https://github.com/lmbstudiocontact/mb5_18/raw/main/Rio2_L2_72027508_Portuguese.bin",
        "name_language": "Portuguese",
        "id_bin_language": "Rio2_L2_72027508_Portuguese"
      },
      {
        "author": "LMB Studio",
        "link_thumb": "https://live.staticflickr.com/65535/51781159010_310aa530da_n.jpg",
        "link_bin": "https://github.com/lmbstudiocontact/mb5_18/raw/main/Rio2_L2_72027508_Russian.bin",
        "name_language": "Russian",
        "id_bin_language": "Rio2_L2_72027508_Russian"
      },
      {
        "author": "LMB Studio",
        "link_thumb": "https://live.staticflickr.com/65535/51779461147_da91007c17_n.jpg",
        "link_bin": "https://github.com/lmbstudiocontact/mb5_18/raw/main/Rio2_L2_72027508_Spanish.bin",
        "name_language": "Spanish",
        "id_bin_language": "Rio2_L2_72027508_Spanish"
      }
    ],
    "array_tags": [
      "lmbstudio"
    ],
    "list_album": [
      {
        "id_album": "-1210862917",
        "link_thumb": "https://live.staticflickr.com/65535/51780526113_90f8534691_n.jpg",
        "title": "Rio 2_L2"
      }
    ]
  },
  {
    "author": "LMB Studio",
    "link_thumb": "https://live.staticflickr.com/65535/51698123080_e8c62bf18a_o.gif",
    "link_bin": "https://github.com/lmbstudiocontact/mb5_31/raw/main/Football_L1_380598802.bin",
    "id_bin": "Football_L1_380598802",
    "list_language": [],
    "array_tags": [
      "lmbstudio"
    ],
    "list_album": [
      {
        "id_album": "-371026089",
        "link_thumb": "https://live.staticflickr.com/65535/51698123080_e8c62bf18a_o.gif",
        "title": "Football_L1"
      }
    ]
  },
  {
    "author": "LMB Studio",
    "link_thumb": "https://live.staticflickr.com/65535/51779355532_06966b8558_o.gif",
    "link_bin": "https://github.com/lmbstudiocontact/mb5_5/raw/main/AngryBirds_L4_-778763138.bin",
    "id_bin": "AngryBirds_L4_-778763138",
    "list_language": [
      {
        "author": "LMB Studio",
        "link_thumb": "https://live.staticflickr.com/65535/51780420788_b14327c8b5_o.gif",
        "link_bin": "https://github.com/lmbstudiocontact/mb5_5/raw/main/AngryBirds_L4_-778763138_English.bin",
        "name_language": "English",
        "id_bin_language": "AngryBirds_L4_-778763138_English"
      },
      {
        "author": "LMB Studio",
        "link_thumb": "https://live.staticflickr.com/65535/51780171806_21b70ef007_o.gif",
        "link_bin": "https://github.com/lmbstudiocontact/mb5_5/raw/main/AngryBirds_L4_-778763138_Portuguese.bin",
        "name_language": "Portuguese",
        "id_bin_language": "AngryBirds_L4_-778763138_Portuguese"
      },
      {
        "author": "LMB Studio",
        "link_thumb": "https://live.staticflickr.com/65535/51781055020_f646bd08e6_o.gif",
        "link_bin": "https://github.com/lmbstudiocontact/mb5_5/raw/main/AngryBirds_L4_-778763138_Russian.bin",
        "name_language": "Russian",
        "id_bin_language": "AngryBirds_L4_-778763138_Russian"
      },
      {
        "author": "LMB Studio",
        "link_thumb": "https://live.staticflickr.com/65535/51780813214_30c2d0ef03_o.gif",
        "link_bin": "https://github.com/lmbstudiocontact/mb5_5/raw/main/AngryBirds_L4_-778763138_Spanish.bin",
        "name_language": "Spanish",
        "id_bin_language": "AngryBirds_L4_-778763138_Spanish"
      }
    ],
    "array_tags": [
      "lmbstudio"
    ],
    "list_album": [
      {
        "id_album": "2112729292",
        "link_thumb": "https://live.staticflickr.com/65535/51779355532_06966b8558_o.gif",
        "title": "Angry Birds_L4"
      }
    ]
  },
  {
    "author": "LMB Studio",
    "link_thumb": "https://live.staticflickr.com/65535/51780469553_a7b92100b1_o.gif",
    "link_bin": "https://github.com/lmbstudiocontact/mb5_41/raw/main/KittyMyMelody_L5_1598076829.bin",
    "id_bin": "KittyMyMelody_L5_1598076829",
    "list_language": [
      {
        "author": "LMB Studio",
        "link_thumb": "https://live.staticflickr.com/65535/51780862819_b415514808_o.gif",
        "link_bin": "https://github.com/lmbstudiocontact/mb5_41/raw/main/KittyMyMelody_L5_1598076829_English.bin",
        "name_language": "English",
        "id_bin_language": "KittyMyMelody_L5_1598076829_English"
      },
      {
        "author": "LMB Studio",
        "link_thumb": "https://live.staticflickr.com/65535/51780220836_989e6a4993_o.gif",
        "link_bin": "https://github.com/lmbstudiocontact/mb5_41/raw/main/KittyMyMelody_L5_1598076829_Portuguese.bin",
        "name_language": "Portuguese",
        "id_bin_language": "KittyMyMelody_L5_1598076829_Portuguese"
      },
      {
        "author": "LMB Studio",
        "link_thumb": "https://live.staticflickr.com/65535/51779404197_0138c88c3b_o.gif",
        "link_bin": "https://github.com/lmbstudiocontact/mb5_41/raw/main/KittyMyMelody_L5_1598076829_Russian.bin",
        "name_language": "Russian",
        "id_bin_language": "KittyMyMelody_L5_1598076829_Russian"
      },
      {
        "author": "LMB Studio",
        "link_thumb": "https://live.staticflickr.com/65535/51780862634_2991dc08f2_o.gif",
        "link_bin": "https://github.com/lmbstudiocontact/mb5_41/raw/main/KittyMyMelody_L5_1598076829_Spanish.bin",
        "name_language": "Spanish",
        "id_bin_language": "KittyMyMelody_L5_1598076829_Spanish"
      }
    ],
    "array_tags": [
      "lmbstudio"
    ],
    "list_album": [
      {
        "id_album": "-378480541",
        "link_thumb": "https://live.staticflickr.com/65535/51780469553_a7b92100b1_o.gif",
        "title": "Kitty \u0026 My Melody_L5"
      }
    ]
  },
  {
    "author": "LMB Studio",
    "link_thumb": "https://live.staticflickr.com/65535/51780440003_4b6b05ecf1_o.gif",
    "link_bin": "https://github.com/lmbstudiocontact/mb5_4/raw/main/DoraemonAnime_L1_-849029921.bin",
    "id_bin": "DoraemonAnime_L1_-849029921",
    "list_language": [],
    "array_tags": [
      "lmbstudio"
    ],
    "list_album": [
      {
        "id_album": "405661391",
        "link_thumb": "https://live.staticflickr.com/65535/51780440003_4b6b05ecf1_o.gif",
        "title": "Doraemon Anime_L1"
      }
    ]
  },
  {
    "author": "LMB Studio",
    "link_thumb": "https://live.staticflickr.com/65535/51780520313_12911c6faa_o.gif",
    "link_bin": "https://github.com/lmbstudiocontact/mb5_20/raw/main/PeaceArt_L7_-988175428.bin",
    "id_bin": "PeaceArt_L7_-988175428",
    "list_language": [],
    "array_tags": [
      "lmbstudio"
    ],
    "list_album": [
      {
        "id_album": "437172985",
        "link_thumb": "https://live.staticflickr.com/65535/51780520313_12911c6faa_o.gif",
        "title": "Peace Art_L7"
      }
    ]
  },
  {
    "author": "LMB Studio",
    "link_thumb": "https://live.staticflickr.com/65535/51780559713_8130d24b94_o.gif",
    "link_bin": "https://github.com/lmbstudiocontact/mb5_20/raw/main/PlantsVsZombies_L5_1174169977.bin",
    "id_bin": "PlantsVsZombies_L5_1174169977",
    "list_language": [
      {
        "author": "LMB Studio",
        "link_thumb": "https://live.staticflickr.com/65535/51780559638_9afc894ab7_o.gif",
        "link_bin": "https://github.com/lmbstudiocontact/mb5_20/raw/main/PlantsVsZombies_L5_1174169977_English.bin",
        "name_language": "English",
        "id_bin_language": "PlantsVsZombies_L5_1174169977_English"
      },
      {
        "author": "LMB Studio",
        "link_thumb": "https://live.staticflickr.com/65535/51779495387_e48f20d47e_o.gif",
        "link_bin": "https://github.com/lmbstudiocontact/mb5_20/raw/main/PlantsVsZombies_L5_1174169977_Portuguese.bin",
        "name_language": "Portuguese",
        "id_bin_language": "PlantsVsZombies_L5_1174169977_Portuguese"
      },
      {
        "author": "LMB Studio",
        "link_thumb": "https://live.staticflickr.com/65535/51779495302_1675ed96f0_o.gif",
        "link_bin": "https://github.com/lmbstudiocontact/mb5_20/raw/main/PlantsVsZombies_L5_1174169977_Russian.bin",
        "name_language": "Russian",
        "id_bin_language": "PlantsVsZombies_L5_1174169977_Russian"
      },
      {
        "author": "LMB Studio",
        "link_thumb": "https://live.staticflickr.com/65535/51780953354_1cf91ca374_o.gif",
        "link_bin": "https://github.com/lmbstudiocontact/mb5_20/raw/main/PlantsVsZombies_L5_1174169977_Spanish.bin",
        "name_language": "Spanish",
        "id_bin_language": "PlantsVsZombies_L5_1174169977_Spanish"
      }
    ],
    "array_tags": [
      "lmbstudio"
    ],
    "list_album": [
      {
        "id_album": "-1426777466",
        "link_thumb": "https://live.staticflickr.com/65535/51780559713_8130d24b94_o.gif",
        "title": "Plants Vs Zombies_L5"
      }
    ]
  },
  {
    "author": "LMB Studio",
    "link_thumb": "https://live.staticflickr.com/65535/51780227721_c236d8a5d6_o.gif",
    "link_bin": "https://github.com/lmbstudiocontact/mb5_31/raw/main/DragonBallAnime_L5_-32108797.bin",
    "id_bin": "DragonBallAnime_L5_-32108797",
    "list_language": [
      {
        "author": "LMB Studio",
        "link_thumb": "https://live.staticflickr.com/65535/51779410827_0c6c8cd50b_o.gif",
        "link_bin": "https://github.com/lmbstudiocontact/mb5_31/raw/main/DragonBallAnime_L5_-32108797_English.bin",
        "name_language": "English",
        "id_bin_language": "DragonBallAnime_L5_-32108797_English"
      },
      {
        "author": "LMB Studio",
        "link_thumb": "https://live.staticflickr.com/65535/51780227506_0420e46d85_o.gif",
        "link_bin": "https://github.com/lmbstudiocontact/mb5_31/raw/main/DragonBallAnime_L5_-32108797_Portuguese.bin",
        "name_language": "Portuguese",
        "id_bin_language": "DragonBallAnime_L5_-32108797_Portuguese"
      },
      {
        "author": "LMB Studio",
        "link_thumb": "https://live.staticflickr.com/65535/51780476183_c62842d176_o.gif",
        "link_bin": "https://github.com/lmbstudiocontact/mb5_31/raw/main/DragonBallAnime_L5_-32108797_Russian.bin",
        "name_language": "Russian",
        "id_bin_language": "DragonBallAnime_L5_-32108797_Russian"
      },
      {
        "author": "LMB Studio",
        "link_thumb": "https://live.staticflickr.com/65535/51779410622_71117e9533_o.gif",
        "link_bin": "https://github.com/lmbstudiocontact/mb5_31/raw/main/DragonBallAnime_L5_-32108797_Spanish.bin",
        "name_language": "Spanish",
        "id_bin_language": "DragonBallAnime_L5_-32108797_Spanish"
      }
    ],
    "array_tags": [
      "lmbstudio"
    ],
    "list_album": [
      {
        "id_album": "1464725224",
        "link_thumb": "https://live.staticflickr.com/65535/51780227721_c236d8a5d6_o.gif",
        "title": "Dragon Ball Anime_L5"
      }
    ]
  },
  {
    "author": "iamstven",
    "link_thumb": "https://live.staticflickr.com/65535/51695042159_06d9e2e47b_o.gif",
    "link_bin": "https://github.com/lmbstudiocontact/mb5_3/raw/main/606.bin",
    "id_bin": "606",
    "list_language": [],
    "array_tags": [
      "date",
      "weather",
      "battery"
    ],
    "list_album": [
      {
        "id_album": "2433880",
        "link_thumb": "https://live.staticflickr.com/65535/51695042159_06d9e2e47b_o.gif",
        "title": "None"
      }
    ]
  }
]